harvest/__init__.py
harvest/config.py
harvest/date_search.py
harvest/extract.py
harvest/post_text.py
harvest/posts.py
harvest/similarity_calculator.py
harvest/utils.py
harvest/cleanup/__init__.py
harvest/cleanup/forum_post.py
harvest/metadata/__init__.py
harvest/metadata/date.py
harvest/metadata/link.py
harvest/metadata/username.py
harvest/metadata/usertext.py
harvest_webforum-1.1.0.data/scripts/extract_to_csv.py
harvest_webforum-1.1.0.data/scripts/serialize_test_data.py
harvest_webforum-1.1.0.dist-info/LICENSE
harvest_webforum-1.1.0.dist-info/METADATA
harvest_webforum-1.1.0.dist-info/WHEEL
harvest_webforum-1.1.0.dist-info/top_level.txt
harvest_webforum-1.1.0.dist-info/RECORD
