Metadata-Version: 2.1
Name: harvest-webforum
Version: 1.1.0
Summary: A toolkit for extracting posts and post metadata from web forums
Home-page: UNKNOWN
Author: Albert Weichselbraun, Roger Waldvogel
Author-email: albert.weichselbraun@fhgr.ch, roger.waldvogel@fhgr.ch
License: Apache-2.0
Platform: UNKNOWN
Requires-Python: >=3.5
Requires-Dist: dateparser
Requires-Dist: flask
Requires-Dist: fuzzywuzzy
Requires-Dist: inscriptis
Requires-Dist: lxml
Requires-Dist: numpy
Requires-Dist: requests
